gtk_stream/__init__.py
gtk_stream/_version.py
gtk_stream/application.py
gtk_stream/command_line.py
gtk_stream/common.py
gtk_stream/parser.py
gtk_stream/properties.py
gtk_stream/documents/__init__.py
gtk_stream/documents/classes/Box.py
gtk_stream/documents/classes/Button.py
gtk_stream/documents/classes/Document.py
gtk_stream/documents/classes/Dropdown.py
gtk_stream/documents/classes/Entry.py
gtk_stream/documents/classes/FlowBox.py
gtk_stream/documents/classes/Frame.py
gtk_stream/documents/classes/Grid.py
gtk_stream/documents/classes/Label.py
gtk_stream/documents/classes/Paned.py
gtk_stream/documents/classes/Picture.py
gtk_stream/documents/classes/ProgressBar.py
gtk_stream/documents/classes/Scale.py
gtk_stream/documents/classes/ScrolledWindow.py
gtk_stream/documents/classes/Separator.py
gtk_stream/documents/classes/Stack.py
gtk_stream/documents/classes/Switch.py
gtk_stream/documents/classes/__init__.py
gtk_stream-0.15.5.dist-info/METADATA
gtk_stream-0.15.5.dist-info/WHEEL
gtk_stream-0.15.5.dist-info/entry_points.txt
gtk_stream-0.15.5.dist-info/top_level.txt
gtk_stream-0.15.5.dist-info/RECORD
